pydsstools/__init__.py
pydsstools/_version.py
pydsstools/_lib/__init__.py
pydsstools/_lib/x64/__init__.py
pydsstools/_lib/x64/core_heclib.cp310-win_amd64.pyd
pydsstools/_lib/x86/__init__.py
pydsstools/core/__init__.py
pydsstools/core/accessors.py
pydsstools/core/grid.py
pydsstools/core/grid_accessors.py
pydsstools/core/transform.py
pydsstools/examples/example.dss
pydsstools/examples/example1.py
pydsstools/examples/example10.py
pydsstools/examples/example11.py
pydsstools/examples/example12.py
pydsstools/examples/example13.py
pydsstools/examples/example14.py
pydsstools/examples/example15.py
pydsstools/examples/example16.py
pydsstools/examples/example2.py
pydsstools/examples/example3.py
pydsstools/examples/example4.py
pydsstools/examples/example5.py
pydsstools/examples/example6.py
pydsstools/examples/example7.py
pydsstools/examples/example8.py
pydsstools/examples/example9.py
pydsstools/examples/example_dss6.dss
pydsstools/examples/test1.py
pydsstools/examples/test2.py
pydsstools/examples/test3.py
pydsstools/heclib/__init__.py
pydsstools/heclib/general.py
pydsstools/heclib/gridv6.py
pydsstools/heclib/utils.py
pydsstools/heclib/dss/HecDss.py
pydsstools/heclib/dss/__init__.py
pydsstools/src/catalog.pyx
pydsstools/src/checlib.pxd
pydsstools/src/constants.pyx
pydsstools/src/core_heclib.c
pydsstools/src/core_heclib.pyx
pydsstools/src/core_heclib_imports.pyx
pydsstools/src/exceptions.pyx
pydsstools/src/grid.pyx
pydsstools/src/hectime.pyx
pydsstools/src/open.pyx
pydsstools/src/paired_data.pyx
pydsstools/src/spatial_tin.pyx
pydsstools/src/time_series.pyx
pydsstools/src/utils.pyx
pydsstools/src/external/dss/headers/hecdss7.h
pydsstools/src/external/dss/headers/hecdssFort.h
pydsstools/src/external/dss/headers/hecdssInternal.h
pydsstools/src/external/dss/headers/heclib.h
pydsstools/src/external/dss/headers/heclib6.h
pydsstools/src/external/dss/headers/heclib7.h
pydsstools/src/external/dss/headers/heclibDate.h
pydsstools/src/external/dss/headers/heclib_wrap.h
pydsstools-2.4.0.dist-info/licenses/LICENSE
pydsstools-2.4.0.dist-info/METADATA
pydsstools-2.4.0.dist-info/WHEEL
pydsstools-2.4.0.dist-info/top_level.txt
pydsstools-2.4.0.dist-info/RECORD
