Metadata-Version: 2.1
Name: pydsstools
Version: 2.4.0
Summary: Python library to read-write HEC-DSS database file
Author-email: Gyan Basyal <gyanBasyalz@gmail.com>
License: MIT License
Project-URL: repository, https://github.com/gyanz/pydsstools
Classifier: Development Status :: 4 - Beta
Classifier: Intended Audience :: Science/Research
Classifier: Operating System :: Microsoft :: Windows :: Windows 10
Classifier: Operating System :: Microsoft :: Windows :: Windows 11
Classifier: Operating System :: Unix
Classifier: Programming Language :: Python :: 3
Classifier: Programming Language :: Python :: 3 :: Only
Classifier: Topic :: Scientific/Engineering
Requires-Python: >=3.8
License-File: LICENSE
Requires-Dist: pandas
Requires-Dist: affine
Requires-Dist: pyproj
Requires-Dist: numpy <2.0.0,>=1.26.0 ; python_version >= "3.11" and python_version < "3.13"
Requires-Dist: numpy >=2.0.0 ; python_version >= "3.13"
Requires-Dist: numpy <2.0.0,>=1.21.5 ; python_version >= "3.8" and python_version < "3.11"
Provides-Extra: test
Requires-Dist: gdal >=3.2.2 ; extra == 'test'
Requires-Dist: rasterio >=1.2.1 ; extra == 'test'
Requires-Dist: matplotlib ; extra == 'test'
